SevenSeg.v
module SevenSeg(
 
    //////////// SEG7 //////////
    output           [7:0]      H,
 
    //////////// KEY //////////
    input            [7:0]     NUM
    
);
 
    reg [7:0] value;
 
//takes decimal number and converts to binary for HEX display based on logic 0 = on, logic 1 = off for each segment
//if NUM = 'd88 is blank(pos)
//if NUM = 'd99 is minus sign
    always @(NUM)
        begin
            case(NUM)
                8'd0: value = 8'b11000000;
                8'd1: value = 8'b11111001;
                8'd2: value = 8'b10100100;
                8'd3: value = 8'b10110000;
                8'd4: value = 8'b10011001;
                8'd5: value = 8'b10010010;
                8'd6: value = 8'b10000010;
                8'd7: value = 8'b11111000;
                8'd8: value = 8'b10000000;
                8'd9: value = 8'b10011000;
                8'd10: value = 8'b10001000; 
                8'd11: value = 8'b10000011;
                8'd12: value = 8'b11000110;
                8'd13: value = 8'b10100001;
                8'd14: value = 8'b10000110;
                8'd15: value = 8'b10001110;
 
                8'd88: value = 8'b11111111;
                8'd99: value = 8'b10111111;
            endcase
        end
 
 
    //the HEX display passed is given whatever value determined above
    assign H[7:0] = value;
 
 
endmodule

daydisplay.v
module daydisplay(
    // input                       clk,
    // input                       reset_n,
    input            [7:0]      day_cntr,

    output           [7:0]      H0,
    output           [7:0]      H1

	//////////// LED //////////
	// output		     [9:0]		LEDR,

	// //////////// SW //////////
	// input 		     [9:0]		SW
);

    reg [7:0] ones_digit;
    reg [7:0] tens_digit;

    always @(day_cntr)begin
            case (day_cntr)
                31: begin
                    tens_digit = 3;
                    ones_digit = 1;
                end
                30: begin
                    tens_digit = 3;
                    ones_digit = 0;
                end
                29: begin
                    tens_digit = 2;
                    ones_digit = 9;
                end
                28: begin
                    tens_digit = 2;
                    ones_digit = 8;
                end
                27: begin
                    tens_digit = 2;
                    ones_digit = 7;
                end
                26: begin
                    tens_digit = 2;
                    ones_digit = 6;
                end
                25: begin
                    tens_digit = 2;
                    ones_digit = 5;
                end
                24: begin
                    tens_digit = 2;
                    ones_digit = 4;
                end
                23: begin
                    tens_digit = 2;
                    ones_digit = 3;
                end
                22: begin
                    tens_digit = 2;
                    ones_digit = 2;
                end
                21: begin
                    tens_digit = 2;
                    ones_digit = 1;
                end
                20: begin
                    tens_digit = 2;
                    ones_digit = 0;
                end
                19: begin
                    tens_digit = 1;
                    ones_digit = 9;
                end
                18: begin
                    tens_digit = 1;
                    ones_digit = 8;
                end
                17: begin
                    tens_digit = 1;
                    ones_digit = 7;
                end
                16: begin
                    tens_digit = 1;
                    ones_digit = 6;
                end
                15: begin
                    tens_digit = 1;
                    ones_digit = 5;
                end
                14: begin
                    tens_digit = 1;
                    ones_digit = 4;
                end
                13: begin
                    tens_digit = 1;
                    ones_digit = 3;
                end
                12: begin
                    tens_digit = 1;
                    ones_digit = 2;
                end
                11: begin
                    tens_digit = 1;
                    ones_digit = 1;
                end
                10: begin
                    tens_digit = 1;
                    ones_digit = 0;
                end
                9: begin
                    tens_digit = 88;
                    ones_digit = 9;
                end
                8: begin
                    tens_digit = 88;
                    ones_digit = 8;
                end
                7: begin
                    tens_digit = 88;
                    ones_digit = 7;
                end
                6: begin
                    tens_digit = 88;
                    ones_digit = 6;
                end
                5: begin
                    tens_digit = 88;
                    ones_digit = 5;
                end
                4: begin
                    tens_digit = 88;
                    ones_digit = 4;
                end
                3: begin
                    tens_digit = 88;
                    ones_digit = 3;
                end
                2: begin
                    tens_digit = 88;
                    ones_digit = 2;
                end
                1: begin
                    tens_digit = 88;
                    ones_digit = 1;
                end
                default: begin
                    tens_digit = 9;
                    ones_digit = 9;
                end
            endcase
        end

    SevenSeg S1(.H(H0), .NUM(ones_digit));
    SevenSeg S2(.H(H1), .NUM(tens_digit));

endmodule

monthday.v
module monthday(
    input                       clk,
    input                       reset_n,
    input            [7:0]      cntr99,

	output           [7:0]      H0,
    output           [7:0]      H1,
    output           [7:0]      H2,

	//////////// SW //////////
	input 		     [9:0]		SW
);

    reg [7:0] month_d;
    reg[7:0] day_cntr;

    always @(cntr99)
        begin
            if(cntr99 <= 8'd31)
                begin
                month_d <= 8'd1;
                day_cntr <= cntr99;
                end
            else if(cntr99 <= 8'd59)
                begin
                    month_d <= 8'd2;
                    day_cntr <= cntr99 - 31;
                end
            else if(cntr99 <= 8'd90)
                begin
                    month_d <= 8'd3;
                    day_cntr <= cntr99 - 31 - 28;
                end
            else
                begin
                    month_d <= 8'd4;
                    day_cntr <= cntr99 - 31 - 28 - 31;
                end
        end

    SevenSeg S0(.H(H2), .NUM(month_d));

    daydisplay D0(.day_cntr(day_cntr), .H0(H0), .H1(H1));

endmodule

counters.v
module counters(
    input                       clk,
    input                       reset_n,

    output           [7:0]      H0,
    output           [7:0]      H1,
    output           [7:0]      H2,
	output		     [7:0]		H4,
	output		     [7:0]		H5,

    //////////// KEY //////////
	input 		     [1:0]		KEY,

	//////////// SW //////////
	input 		     [9:0]		SW
);

    reg [7:0] cntr1;
    reg [7:0] cntr2;
    reg [7:0] cntr99;

    always @(posedge clk, negedge reset_n)
        begin
            if(reset_n == 0)
                begin
                    cntr2 <= 8'd88;
                    cntr1 <= 8'd1;
                    cntr99 <= 8'd1;
                end
            else
                begin
                    if(cntr1 != 9)
                        begin
                            cntr2 <= cntr2;
                            cntr1 <= cntr1 + 1;
                            cntr99 <= cntr99 + 1;
                        end
                    else if(cntr1 == 9)
                        begin
                            if(cntr2 == 8'd88)
                                begin
                                    cntr2 <= 8'd1;
                                    cntr1 <= 8'd0;
                                    cntr99 <= cntr99 + 1;
                                end
                            else if(cntr2 == 8'd9)
                                begin
                                    cntr2 <= 8'd88;
                                    cntr1 <= 8'd1;
                                    cntr99 <= 8'd1;
                                end
                            else
                                begin
                                    cntr2 <= cntr2 + 1;
                                    cntr1 <= 8'd0;
                                    cntr99 <= cntr99 + 1;
                                end
                        end
                end
        end

    monthday M0(.clk(clk), .reset_n(reset_n), .cntr99(cntr99), .H0(H0), .H1(H1), .H2(H2), .SW(SW));

    SevenSeg W0(.H(H4), .NUM(cntr1));
    SevenSeg W1(.H(H5), .NUM(cntr2));

endmodule

tb_BCD.v
`timescale 1 ns / 100 ps

module tb_BCD();

    reg clk;
    reg Rn;
    wire [7:0] HEX0;
    wire [7:0] HEX1;
    wire [7:0] HEX2;
    wire [7:0] HEX4;
    wire [7:0] HEX5;
    wire [1:0] K;
    wire [9:0] sw;

    counters U0 (
        .clk(clk),
        .reset_n(Rn),
        .H0(HEX0),
        .H1(HEX1),
        .H2(HEX2),
        .H4(HEX4),
        .H5(HEX5),
        .KEY(K),
        .SW(sw)
    );

    initial
        begin
            clk = 1'b0;
            Rn = 1'b0;
        #10 Rn = 1'b1;
        end

    always
        #5 clk = ~clk;

    initial
        begin
            $dumpfile("output.vcd");
            $dumpvars;
            $display("Starting simulation");
        end   

    initial
        begin
        $monitor("%d,\t%b,\t%b,\t%d", $time, clk, Rn, HEX4, HEX5);        
        end

        initial
            begin
            $display("Simulation ended.");
            #1300 $finish;
            end
        
endmodule

clock_divider.v
module clock_divider(

	//////////// CLOCK //////////
	input 		          		clk,
    input                       reset_n,
    output                      slower_clk      //calculate correct size!                
);

    parameter clk_div = 0;

    reg [23:0] div_cntr; //calculate correct size!
    reg slw_clk;

    always @(posedge clk, negedge reset_n)
        begin
            if(reset_n == 0)
                begin
                    div_cntr <= 0;
                    slw_clk <= 0;
                end
            else if(div_cntr == clk_div - 1)
                begin
                    div_cntr <= 0;
                    slw_clk <= ~slw_clk;
                end
            else
                begin
                    div_cntr <= div_cntr + 1;
                end
        end

    assign slower_clk = slw_clk;

endmodule

Lab2.v

//=======================================================
//  This code is generated by Terasic System Builder
//=======================================================

module Lab2(

	//////////// CLOCK //////////
	input 		          		ADC_CLK_10,
	input 		          		MAX10_CLK1_50,
	input 		          		MAX10_CLK2_50,

	//////////// SEG7 //////////
	output		     [7:0]		HEX0,
	output		     [7:0]		HEX1,
	output		     [7:0]		HEX2,
	output		     [7:0]		HEX3,
	output		     [7:0]		HEX4,
	output		     [7:0]		HEX5,

	//////////// KEY //////////
	input 		     [1:0]		KEY,

	//////////// LED //////////
	output		     [9:0]		LEDR,

	//////////// SW //////////
	input 		     [9:0]		SW
);
	wire s_clk;
	reg latch_out = 1'b0;
	wire latch;

	SevenSeg T0(.H(HEX3), .NUM(8'd88));

	always @(negedge KEY[0])
		begin
			latch_out <= ~latch_out;	
		end

	assign latch = latch_out;
	assign LEDR[0] = ~latch_out;

	assign LEDR[1] = s_clk;

	clock_divider #(5_000_000) U0(.clk(ADC_CLK_10), .reset_n(latch), .slower_clk(s_clk));
	clock_divider #(1_000_000) U1(.clk(ADC_CLK_10), .reset_n(latch), .slower_clk(s_clk));

	reg div_val = 1'b1;
	wire val;

	always @(negedge KEY[1])
		begin
			div_val <= ~div_val;
		end

	assign val = div_val;

	// clock_choice L0(.);

	counters C0(.clk(s_clk), .reset_n(latch), .H0(HEX0), .H1(HEX1), .H2(HEX2), .H4(HEX4), .H5(HEX5), .KEY(KEY), .SW(SW));


endmodule

output.vcd
$date
	Mon Nov 04 22:45:15 2019
$end
$version
	Icarus Verilog
$end
$timescale
	100ps
$end
$scope module Lab2 $end
$var wire 1 ! ADC_CLK_10 $end
$var wire 2 " KEY [1:0] $end
$var wire 1 # MAX10_CLK1_50 $end
$var wire 1 $ MAX10_CLK2_50 $end
$var wire 10 % SW [9:0] $end
$var wire 1 & latch $end
$var wire 1 ' s_clk $end
$var wire 1 ( val $end
$var wire 10 ) LEDR [9:0] $end
$var wire 8 * HEX5 [7:0] $end
$var wire 8 + HEX4 [7:0] $end
$var wire 8 , HEX3 [7:0] $end
$var wire 8 - HEX2 [7:0] $end
$var wire 8 . HEX1 [7:0] $end
$var wire 8 / HEX0 [7:0] $end
$var reg 1 0 div_val $end
$var reg 1 1 latch_out $end
$scope module C0 $end
$var wire 2 2 KEY [1:0] $end
$var wire 10 3 SW [9:0] $end
$var wire 1 ' clk $end
$var wire 1 & reset_n $end
$var wire 8 4 H5 [7:0] $end
$var wire 8 5 H4 [7:0] $end
$var wire 8 6 H2 [7:0] $end
$var wire 8 7 H1 [7:0] $end
$var wire 8 8 H0 [7:0] $end
$var reg 8 9 cntr1 [7:0] $end
$var reg 8 : cntr2 [7:0] $end
$var reg 8 ; cntr99 [7:0] $end
$scope module M0 $end
$var wire 10 < SW [9:0] $end
$var wire 1 ' clk $end
$var wire 8 = cntr99 [7:0] $end
$var wire 1 & reset_n $end
$var wire 8 > H2 [7:0] $end
$var wire 8 ? H1 [7:0] $end
$var wire 8 @ H0 [7:0] $end
$var reg 8 A day_cntr [7:0] $end
$var reg 8 B month_d [7:0] $end
$scope module D0 $end
$var wire 8 C day_cntr [7:0] $end
$var wire 8 D H1 [7:0] $end
$var wire 8 E H0 [7:0] $end
$var reg 8 F ones_digit [7:0] $end
$var reg 8 G tens_digit [7:0] $end
$scope module S1 $end
$var wire 8 H H [7:0] $end
$var wire 8 I NUM [7:0] $end
$var reg 8 J value [7:0] $end
$upscope $end
$scope module S2 $end
$var wire 8 K H [7:0] $end
$var wire 8 L NUM [7:0] $end
$var reg 8 M value [7:0] $end
$upscope $end
$upscope $end
$scope module S0 $end
$var wire 8 N H [7:0] $end
$var wire 8 O NUM [7:0] $end
$var reg 8 P value [7:0] $end
$upscope $end
$upscope $end
$scope module W0 $end
$var wire 8 Q H [7:0] $end
$var wire 8 R NUM [7:0] $end
$var reg 8 S value [7:0] $end
$upscope $end
$scope module W1 $end
$var wire 8 T H [7:0] $end
$var wire 8 U NUM [7:0] $end
$var reg 8 V value [7:0] $end
$upscope $end
$upscope $end
$scope module T0 $end
$var wire 8 W H [7:0] $end
$var wire 8 X NUM [7:0] $end
$var reg 8 Y value [7:0] $end
$upscope $end
$scope module U0 $end
$var wire 1 ! clk $end
$var wire 1 & reset_n $end
$var wire 1 ' slower_clk $end
$var reg 24 Z div_cntr [23:0] $end
$var reg 1 [ slw_clk $end
$upscope $end
$scope module U1 $end
$var wire 1 ! clk $end
$var wire 1 & reset_n $end
$var wire 1 ' slower_clk $end
$var reg 24 \ div_cntr [23:0] $end
$var reg 1 ] slw_clk $end
$upscope $end
$upscope $end
$scope module tb_BCD $end
$var wire 2 ^ K [1:0] $end
$var wire 10 _ sw [9:0] $end
$var wire 8 ` HEX5 [7:0] $end
$var wire 8 a HEX4 [7:0] $end
$var wire 8 b HEX2 [7:0] $end
$var wire 8 c HEX1 [7:0] $end
$var wire 8 d HEX0 [7:0] $end
$var reg 1 e Rn $end
$var reg 1 f clk $end
$scope module U0 $end
$var wire 2 g KEY [1:0] $end
$var wire 10 h SW [9:0] $end
$var wire 1 f clk $end
$var wire 1 e reset_n $end
$var wire 8 i H5 [7:0] $end
$var wire 8 j H4 [7:0] $end
$var wire 8 k H2 [7:0] $end
$var wire 8 l H1 [7:0] $end
$var wire 8 m H0 [7:0] $end
$var reg 8 n cntr1 [7:0] $end
$var reg 8 o cntr2 [7:0] $end
$var reg 8 p cntr99 [7:0] $end
$scope module M0 $end
$var wire 10 q SW [9:0] $end
$var wire 1 f clk $end
$var wire 8 r cntr99 [7:0] $end
$var wire 1 e reset_n $end
$var wire 8 s H2 [7:0] $end
$var wire 8 t H1 [7:0] $end
$var wire 8 u H0 [7:0] $end
$var reg 8 v day_cntr [7:0] $end
$var reg 8 w month_d [7:0] $end
$scope module D0 $end
$var wire 8 x day_cntr [7:0] $end
$var wire 8 y H1 [7:0] $end
$var wire 8 z H0 [7:0] $end
$var reg 8 { ones_digit [7:0] $end
$var reg 8 | tens_digit [7:0] $end
$scope module S1 $end
$var wire 8 } H [7:0] $end
$var wire 8 ~ NUM [7:0] $end
$var reg 8 !" value [7:0] $end
$upscope $end
$scope module S2 $end
$var wire 8 "" H [7:0] $end
$var wire 8 #" NUM [7:0] $end
$var reg 8 $" value [7:0] $end
$upscope $end
$upscope $end
$scope module S0 $end
$var wire 8 %" H [7:0] $end
$var wire 8 &" NUM [7:0] $end
$var reg 8 '" value [7:0] $end
$upscope $end
$upscope $end
$scope module W0 $end
$var wire 8 (" H [7:0] $end
$var wire 8 )" NUM [7:0] $end
$var reg 8 *" value [7:0] $end
$upscope $end
$scope module W1 $end
$var wire 8 +" H [7:0] $end
$var wire 8 ," NUM [7:0] $end
$var reg 8 -" value [7:0] $end
$upscope $end
$upscope $end
$upscope $end
$enddefinitions $end
#0
$dumpvars
b11111111 -"
b1011000 ,"
b11111111 +"
b11111001 *"
b1 )"
b11111001 ("
b11111001 '"
b1 &"
b11111001 %"
b11111111 $"
b1011000 #"
b11111111 ""
b11111001 !"
b1 ~
b11111001 }
b1011000 |
b1 {
b11111001 z
b11111111 y
b1 x
b1 w
b1 v
b11111001 u
b11111111 t
b11111001 s
b1 r
bz q
b1 p
b1011000 o
b1 n
b11111001 m
b11111111 l
b11111001 k
b11111001 j
b11111111 i
bz h
bz g
0f
0e
b11111001 d
b11111111 c
b11111001 b
b11111001 a
b11111111 `
bz _
bz ^
0]
b0 \
0[
b0 Z
b11111111 Y
b1011000 X
b11111111 W
b11111111 V
b1011000 U
b11111111 T
b11111001 S
b1 R
b11111001 Q
b11111001 P
b1 O
b11111001 N
b11111111 M
b1011000 L
b11111111 K
b11111001 J
b1 I
b11111001 H
b1011000 G
b1 F
b11111001 E
b11111111 D
b1 C
b1 B
b1 A
b11111001 @
b11111111 ?
b11111001 >
b1 =
bz <
b1 ;
b1011000 :
b1 9
b11111001 8
b11111111 7
b11111001 6
b11111001 5
b11111111 4
bz 3
bz 2
01
10
b11111001 /
b11111111 .
b11111001 -
b11111111 ,
b11111001 +
b11111111 *
bz01 )
1(
0'
0&
bz %
z$
z#
bz "
z!
$end
#50
1f
#100
0f
1e
#150
b10100100 d
b10100100 m
b10100100 u
b10100100 z
b10100100 }
b10100100 !"
b10 {
b10 ~
b10 v
b10 x
b10100100 a
b10100100 j
b10100100 ("
b10100100 *"
b10 p
b10 r
b10 n
b10 )"
1f
#200
0f
#250
b10110000 d
b10110000 m
b10110000 u
b10110000 z
b10110000 }
b10110000 !"
b11 {
b11 ~
b11 v
b11 x
b10110000 a
b10110000 j
b10110000 ("
b10110000 *"
b11 p
b11 r
b11 n
b11 )"
1f
#300
0f
#350
b10011001 d
b10011001 m
b10011001 u
b10011001 z
b10011001 }
b10011001 !"
b100 {
b100 ~
b100 v
b100 x
b10011001 a
b10011001 j
b10011001 ("
b10011001 *"
b100 p
b100 r
b100 n
b100 )"
1f
#400
0f
#450
b10010010 d
b10010010 m
b10010010 u
b10010010 z
b10010010 }
b10010010 !"
b101 {
b101 ~
b101 v
b101 x
b10010010 a
b10010010 j
b10010010 ("
b10010010 *"
b101 p
b101 r
b101 n
b101 )"
1f
#500
0f
#550
b10000010 d
b10000010 m
b10000010 u
b10000010 z
b10000010 }
b10000010 !"
b110 {
b110 ~
b110 v
b110 x
b10000010 a
b10000010 j
b10000010 ("
b10000010 *"
b110 p
b110 r
b110 n
b110 )"
1f
#600
0f
#650
b11111000 d
b11111000 m
b11111000 u
b11111000 z
b11111000 }
b11111000 !"
b111 {
b111 ~
b111 v
b111 x
b11111000 a
b11111000 j
b11111000 ("
b11111000 *"
b111 p
b111 r
b111 n
b111 )"
1f
#700
0f
#750
b10000000 d
b10000000 m
b10000000 u
b10000000 z
b10000000 }
b10000000 !"
b1000 {
b1000 ~
b1000 v
b1000 x
b10000000 a
b10000000 j
b10000000 ("
b10000000 *"
b1000 p
b1000 r
b1000 n
b1000 )"
1f
#800
0f
#850
b10011000 d
b10011000 m
b10011000 u
b10011000 z
b10011000 }
b10011000 !"
b1001 {
b1001 ~
b1001 v
b1001 x
b10011000 a
b10011000 j
b10011000 ("
b10011000 *"
b1001 p
b1001 r
b1001 n
b1001 )"
1f
#900
0f
#950
b11000000 d
b11000000 m
b11000000 u
b11000000 z
b11000000 }
b11000000 !"
b11111001 c
b11111001 l
b11111001 t
b11111001 y
b11111001 ""
b11111001 $"
b0 {
b0 ~
b1 |
b1 #"
b1010 v
b1010 x
b11000000 a
b11000000 j
b11000000 ("
b11000000 *"
b11111001 `
b11111001 i
b11111001 +"
b11111001 -"
b1010 p
b1010 r
b0 n
b0 )"
b1 o
b1 ,"
1f
#1000
0f
#1050
b11111001 d
b11111001 m
b11111001 u
b11111001 z
b11111001 }
b11111001 !"
b1 {
b1 ~
b1011 v
b1011 x
b11111001 a
b11111001 j
b11111001 ("
b11111001 *"
b1011 p
b1011 r
b1 n
b1 )"
1f
#1100
0f
#1150
b10100100 d
b10100100 m
b10100100 u
b10100100 z
b10100100 }
b10100100 !"
b10 {
b10 ~
b1100 v
b1100 x
b10100100 a
b10100100 j
b10100100 ("
b10100100 *"
b1100 p
b1100 r
b10 n
b10 )"
1f
#1200
0f
#1250
b10110000 d
b10110000 m
b10110000 u
b10110000 z
b10110000 }
b10110000 !"
b11 {
b11 ~
b1101 v
b1101 x
b10110000 a
b10110000 j
b10110000 ("
b10110000 *"
b1101 p
b1101 r
b11 n
b11 )"
1f
#1300
0f
#1350
b10011001 d
b10011001 m
b10011001 u
b10011001 z
b10011001 }
b10011001 !"
b100 {
b100 ~
b1110 v
b1110 x
b10011001 a
b10011001 j
b10011001 ("
b10011001 *"
b1110 p
b1110 r
b100 n
b100 )"
1f
#1400
0f
#1450
b10010010 d
b10010010 m
b10010010 u
b10010010 z
b10010010 }
b10010010 !"
b101 {
b101 ~
b1111 v
b1111 x
b10010010 a
b10010010 j
b10010010 ("
b10010010 *"
b1111 p
b1111 r
b101 n
b101 )"
1f
#1500
0f
#1550
b10000010 d
b10000010 m
b10000010 u
b10000010 z
b10000010 }
b10000010 !"
b110 {
b110 ~
b10000 v
b10000 x
b10000010 a
b10000010 j
b10000010 ("
b10000010 *"
b10000 p
b10000 r
b110 n
b110 )"
1f
#1600
0f
#1650
b11111000 d
b11111000 m
b11111000 u
b11111000 z
b11111000 }
b11111000 !"
b111 {
b111 ~
b10001 v
b10001 x
b11111000 a
b11111000 j
b11111000 ("
b11111000 *"
b10001 p
b10001 r
b111 n
b111 )"
1f
#1700
0f
#1750
b10000000 d
b10000000 m
b10000000 u
b10000000 z
b10000000 }
b10000000 !"
b1000 {
b1000 ~
b10010 v
b10010 x
b10000000 a
b10000000 j
b10000000 ("
b10000000 *"
b10010 p
b10010 r
b1000 n
b1000 )"
1f
#1800
0f
#1850
b10011000 d
b10011000 m
b10011000 u
b10011000 z
b10011000 }
b10011000 !"
b1001 {
b1001 ~
b10011 v
b10011 x
b10011000 a
b10011000 j
b10011000 ("
b10011000 *"
b10011 p
b10011 r
b1001 n
b1001 )"
1f
#1900
0f
#1950
b11000000 d
b11000000 m
b11000000 u
b11000000 z
b11000000 }
b11000000 !"
b10100100 c
b10100100 l
b10100100 t
b10100100 y
b10100100 ""
b10100100 $"
b0 {
b0 ~
b10 |
b10 #"
b10100 v
b10100 x
b11000000 a
b11000000 j
b11000000 ("
b11000000 *"
b10100100 `
b10100100 i
b10100100 +"
b10100100 -"
b10100 p
b10100 r
b0 n
b0 )"
b10 o
b10 ,"
1f
#2000
0f
#2050
b11111001 d
b11111001 m
b11111001 u
b11111001 z
b11111001 }
b11111001 !"
b1 {
b1 ~
b10101 v
b10101 x
b11111001 a
b11111001 j
b11111001 ("
b11111001 *"
b10101 p
b10101 r
b1 n
b1 )"
1f
#2100
0f
#2150
b10100100 d
b10100100 m
b10100100 u
b10100100 z
b10100100 }
b10100100 !"
b10 {
b10 ~
b10110 v
b10110 x
b10100100 a
b10100100 j
b10100100 ("
b10100100 *"
b10110 p
b10110 r
b10 n
b10 )"
1f
#2200
0f
#2250
b10110000 d
b10110000 m
b10110000 u
b10110000 z
b10110000 }
b10110000 !"
b11 {
b11 ~
b10111 v
b10111 x
b10110000 a
b10110000 j
b10110000 ("
b10110000 *"
b10111 p
b10111 r
b11 n
b11 )"
1f
#2300
0f
#2350
b10011001 d
b10011001 m
b10011001 u
b10011001 z
b10011001 }
b10011001 !"
b100 {
b100 ~
b11000 v
b11000 x
b10011001 a
b10011001 j
b10011001 ("
b10011001 *"
b11000 p
b11000 r
b100 n
b100 )"
1f
#2400
0f
#2450
b10010010 d
b10010010 m
b10010010 u
b10010010 z
b10010010 }
b10010010 !"
b101 {
b101 ~
b11001 v
b11001 x
b10010010 a
b10010010 j
b10010010 ("
b10010010 *"
b11001 p
b11001 r
b101 n
b101 )"
1f
#2500
0f
#2550
b10000010 d
b10000010 m
b10000010 u
b10000010 z
b10000010 }
b10000010 !"
b110 {
b110 ~
b11010 v
b11010 x
b10000010 a
b10000010 j
b10000010 ("
b10000010 *"
b11010 p
b11010 r
b110 n
b110 )"
1f
#2600
0f
#2650
b11111000 d
b11111000 m
b11111000 u
b11111000 z
b11111000 }
b11111000 !"
b111 {
b111 ~
b11011 v
b11011 x
b11111000 a
b11111000 j
b11111000 ("
b11111000 *"
b11011 p
b11011 r
b111 n
b111 )"
1f
#2700
0f
#2750
b10000000 d
b10000000 m
b10000000 u
b10000000 z
b10000000 }
b10000000 !"
b1000 {
b1000 ~
b11100 v
b11100 x
b10000000 a
b10000000 j
b10000000 ("
b10000000 *"
b11100 p
b11100 r
b1000 n
b1000 )"
1f
#2800
0f
#2850
b10011000 d
b10011000 m
b10011000 u
b10011000 z
b10011000 }
b10011000 !"
b1001 {
b1001 ~
b11101 v
b11101 x
b10011000 a
b10011000 j
b10011000 ("
b10011000 *"
b11101 p
b11101 r
b1001 n
b1001 )"
1f
#2900
0f
#2950
b11000000 d
b11000000 m
b11000000 u
b11000000 z
b11000000 }
b11000000 !"
b10110000 c
b10110000 l
b10110000 t
b10110000 y
b10110000 ""
b10110000 $"
b0 {
b0 ~
b11 |
b11 #"
b11110 v
b11110 x
b11000000 a
b11000000 j
b11000000 ("
b11000000 *"
b10110000 `
b10110000 i
b10110000 +"
b10110000 -"
b11110 p
b11110 r
b0 n
b0 )"
b11 o
b11 ,"
1f
#3000
0f
#3050
b11111001 d
b11111001 m
b11111001 u
b11111001 z
b11111001 }
b11111001 !"
b1 {
b1 ~
b11111 v
b11111 x
b11111001 a
b11111001 j
b11111001 ("
b11111001 *"
b11111 p
b11111 r
b1 n
b1 )"
1f
#3100
0f
#3150
b11111111 c
b11111111 l
b11111111 t
b11111111 y
b11111111 ""
b11111111 $"
b1011000 |
b1011000 #"
b10100100 b
b10100100 k
b10100100 s
b10100100 %"
b10100100 '"
b1 v
b1 x
b10 w
b10 &"
b10100100 a
b10100100 j
b10100100 ("
b10100100 *"
b100000 p
b100000 r
b10 n
b10 )"
1f
#3200
0f
#3250
b10100100 d
b10100100 m
b10100100 u
b10100100 z
b10100100 }
b10100100 !"
b10 {
b10 ~
b10 v
b10 x
b10110000 a
b10110000 j
b10110000 ("
b10110000 *"
b100001 p
b100001 r
b11 n
b11 )"
1f
#3300
0f
#3350
b10110000 d
b10110000 m
b10110000 u
b10110000 z
b10110000 }
b10110000 !"
b11 {
b11 ~
b11 v
b11 x
b10011001 a
b10011001 j
b10011001 ("
b10011001 *"
b100010 p
b100010 r
b100 n
b100 )"
1f
#3400
0f
#3450
b10011001 d
b10011001 m
b10011001 u
b10011001 z
b10011001 }
b10011001 !"
b100 {
b100 ~
b100 v
b100 x
b10010010 a
b10010010 j
b10010010 ("
b10010010 *"
b100011 p
b100011 r
b101 n
b101 )"
1f
#3500
0f
#3550
b10010010 d
b10010010 m
b10010010 u
b10010010 z
b10010010 }
b10010010 !"
b101 {
b101 ~
b101 v
b101 x
b10000010 a
b10000010 j
b10000010 ("
b10000010 *"
b100100 p
b100100 r
b110 n
b110 )"
1f
#3600
0f
#3650
b10000010 d
b10000010 m
b10000010 u
b10000010 z
b10000010 }
b10000010 !"
b110 {
b110 ~
b110 v
b110 x
b11111000 a
b11111000 j
b11111000 ("
b11111000 *"
b100101 p
b100101 r
b111 n
b111 )"
1f
#3700
0f
#3750
b11111000 d
b11111000 m
b11111000 u
b11111000 z
b11111000 }
b11111000 !"
b111 {
b111 ~
b111 v
b111 x
b10000000 a
b10000000 j
b10000000 ("
b10000000 *"
b100110 p
b100110 r
b1000 n
b1000 )"
1f
#3800
0f
#3850
b10000000 d
b10000000 m
b10000000 u
b10000000 z
b10000000 }
b10000000 !"
b1000 {
b1000 ~
b1000 v
b1000 x
b10011000 a
b10011000 j
b10011000 ("
b10011000 *"
b100111 p
b100111 r
b1001 n
b1001 )"
1f
#3900
0f
#3950
b10011000 d
b10011000 m
b10011000 u
b10011000 z
b10011000 }
b10011000 !"
b1001 {
b1001 ~
b1001 v
b1001 x
b11000000 a
b11000000 j
b11000000 ("
b11000000 *"
b10011001 `
b10011001 i
b10011001 +"
b10011001 -"
b101000 p
b101000 r
b0 n
b0 )"
b100 o
b100 ,"
1f
#4000
0f
#4050
b11000000 d
b11000000 m
b11000000 u
b11000000 z
b11000000 }
b11000000 !"
b11111001 c
b11111001 l
b11111001 t
b11111001 y
b11111001 ""
b11111001 $"
b0 {
b0 ~
b1 |
b1 #"
b1010 v
b1010 x
b11111001 a
b11111001 j
b11111001 ("
b11111001 *"
b101001 p
b101001 r
b1 n
b1 )"
1f
#4100
0f
#4150
b11111001 d
b11111001 m
b11111001 u
b11111001 z
b11111001 }
b11111001 !"
b1 {
b1 ~
b1011 v
b1011 x
b10100100 a
b10100100 j
b10100100 ("
b10100100 *"
b101010 p
b101010 r
b10 n
b10 )"
1f
#4200
0f
#4250
b10100100 d
b10100100 m
b10100100 u
b10100100 z
b10100100 }
b10100100 !"
b10 {
b10 ~
b1100 v
b1100 x
b10110000 a
b10110000 j
b10110000 ("
b10110000 *"
b101011 p
b101011 r
b11 n
b11 )"
1f
#4300
0f
#4350
b10110000 d
b10110000 m
b10110000 u
b10110000 z
b10110000 }
b10110000 !"
b11 {
b11 ~
b1101 v
b1101 x
b10011001 a
b10011001 j
b10011001 ("
b10011001 *"
b101100 p
b101100 r
b100 n
b100 )"
1f
#4400
0f
#4450
b10011001 d
b10011001 m
b10011001 u
b10011001 z
b10011001 }
b10011001 !"
b100 {
b100 ~
b1110 v
b1110 x
b10010010 a
b10010010 j
b10010010 ("
b10010010 *"
b101101 p
b101101 r
b101 n
b101 )"
1f
#4500
0f
#4550
b10010010 d
b10010010 m
b10010010 u
b10010010 z
b10010010 }
b10010010 !"
b101 {
b101 ~
b1111 v
b1111 x
b10000010 a
b10000010 j
b10000010 ("
b10000010 *"
b101110 p
b101110 r
b110 n
b110 )"
1f
#4600
0f
#4650
b10000010 d
b10000010 m
b10000010 u
b10000010 z
b10000010 }
b10000010 !"
b110 {
b110 ~
b10000 v
b10000 x
b11111000 a
b11111000 j
b11111000 ("
b11111000 *"
b101111 p
b101111 r
b111 n
b111 )"
1f
#4700
0f
#4750
b11111000 d
b11111000 m
b11111000 u
b11111000 z
b11111000 }
b11111000 !"
b111 {
b111 ~
b10001 v
b10001 x
b10000000 a
b10000000 j
b10000000 ("
b10000000 *"
b110000 p
b110000 r
b1000 n
b1000 )"
1f
#4800
0f
#4850
b10000000 d
b10000000 m
b10000000 u
b10000000 z
b10000000 }
b10000000 !"
b1000 {
b1000 ~
b10010 v
b10010 x
b10011000 a
b10011000 j
b10011000 ("
b10011000 *"
b110001 p
b110001 r
b1001 n
b1001 )"
1f
#4900
0f
#4950
b10011000 d
b10011000 m
b10011000 u
b10011000 z
b10011000 }
b10011000 !"
b1001 {
b1001 ~
b10011 v
b10011 x
b11000000 a
b11000000 j
b11000000 ("
b11000000 *"
b10010010 `
b10010010 i
b10010010 +"
b10010010 -"
b110010 p
b110010 r
b0 n
b0 )"
b101 o
b101 ,"
1f
#5000
0f
