clock_divider.v
module clock_divider(

	//////////// CLOCK //////////
	input 		          		clk,
    input                       reset_n,
    output                      slower_clk      //calculate correct size!                
);

    parameter clk_div = 0;

    reg [23:0] div_cntr; //calculate correct size!
    reg slw_clk;

    always @(posedge clk, negedge reset_n)
        begin
            if(reset_n == 0)
                begin
                    div_cntr <= 0;
                    slw_clk <= 0;
                end
            else if(div_cntr == clk_div - 1)
                begin
                    div_cntr <= 0;
                    slw_clk <= ~slw_clk;
                end
            else
                begin
                    div_cntr <= div_cntr + 1;
                end
        end

    assign slower_clk = slw_clk;

endmodule

tb_clkdiv.v
`timescale 1 ns / 100 ps

module tb_clkdiv();

    reg clk;
    reg Rn;
    wire SCLK;

    clock_divider #(5) U0 (
        .clk(clk),
        .reset_n(Rn),
        .slower_clk(SCLK)
    );

    initial
        begin
            clk = 1'b0;
            Rn = 1'b0;
        #10 Rn = 1'b1;
        end

    always
        #5 clk = ~clk;

    initial
        begin
            $dumpfile("output.vcd");
            $dumpvars;
            $display("Starting simulation");
        end   

    initial
        begin
        $monitor("%d,\t%b,\t%b", $time, clk, Rn, SCLK);        
        end

        initial
            begin
            $display("Simulation ended.");
            #1000 $finish;
            end
        
endmodule

SevenSeg.v
module SevenSeg(
 
    //////////// SEG7 //////////
    output           [7:0]      H,
 
    //////////// KEY //////////
    input            [7:0]     NUM
    
);
 
    reg [7:0] value;
 
//takes decimal number and converts to binary for HEX display based on logic 0 = on, logic 1 = off for each segment
//if NUM = 'd88 is blank(pos)
//if NUM = 'd99 is minus sign
    always @(NUM)
        begin
            case(NUM)
                8'd0: value = 8'b11000000;
                8'd1: value = 8'b11111001;
                8'd2: value = 8'b10100100;
                8'd3: value = 8'b10110000;
                8'd4: value = 8'b10011001;
                8'd5: value = 8'b10010010;
                8'd6: value = 8'b10000010;
                8'd7: value = 8'b11111000;
                8'd8: value = 8'b10000000;
                8'd9: value = 8'b10011000;
                8'd10: value = 8'b10001000; 
                8'd11: value = 8'b10000011;
                8'd12: value = 8'b11000110;
                8'd13: value = 8'b10100001;
                8'd14: value = 8'b10000110;
                8'd15: value = 8'b10001110;
 
                8'd88: value = 8'b11111111;
                8'd99: value = 8'b10111111;
            endcase
        end
 
 
    //the HEX display passed is given whatever value determined above
    assign H[7:0] = value;
 
 
endmodule

daydisplay.v
module daydisplay(
    // input                       clk,
    // input                       reset_n,
    input            [7:0]      day_cntr,

    output           [7:0]      H0,
    output           [7:0]      H1

	//////////// LED //////////
	// output		     [9:0]		LEDR,

	// //////////// SW //////////
	// input 		     [9:0]		SW
);

    reg [7:0] ones_digit;
    reg [7:0] tens_digit;

    always @(day_cntr)begin
            case (day_cntr)
                31: begin
                    tens_digit = 3;
                    ones_digit = 1;
                end
                30: begin
                    tens_digit = 3;
                    ones_digit = 0;
                end
                29: begin
                    tens_digit = 2;
                    ones_digit = 9;
                end
                28: begin
                    tens_digit = 2;
                    ones_digit = 8;
                end
                27: begin
                    tens_digit = 2;
                    ones_digit = 7;
                end
                26: begin
                    tens_digit = 2;
                    ones_digit = 6;
                end
                25: begin
                    tens_digit = 2;
                    ones_digit = 5;
                end
                24: begin
                    tens_digit = 2;
                    ones_digit = 4;
                end
                23: begin
                    tens_digit = 2;
                    ones_digit = 3;
                end
                22: begin
                    tens_digit = 2;
                    ones_digit = 2;
                end
                21: begin
                    tens_digit = 2;
                    ones_digit = 1;
                end
                20: begin
                    tens_digit = 2;
                    ones_digit = 0;
                end
                19: begin
                    tens_digit = 1;
                    ones_digit = 9;
                end
                18: begin
                    tens_digit = 1;
                    ones_digit = 8;
                end
                17: begin
                    tens_digit = 1;
                    ones_digit = 7;
                end
                16: begin
                    tens_digit = 1;
                    ones_digit = 6;
                end
                15: begin
                    tens_digit = 1;
                    ones_digit = 5;
                end
                14: begin
                    tens_digit = 1;
                    ones_digit = 4;
                end
                13: begin
                    tens_digit = 1;
                    ones_digit = 3;
                end
                12: begin
                    tens_digit = 1;
                    ones_digit = 2;
                end
                11: begin
                    tens_digit = 1;
                    ones_digit = 1;
                end
                10: begin
                    tens_digit = 1;
                    ones_digit = 0;
                end
                9: begin
                    tens_digit = 88;
                    ones_digit = 9;
                end
                8: begin
                    tens_digit = 88;
                    ones_digit = 8;
                end
                7: begin
                    tens_digit = 88;
                    ones_digit = 7;
                end
                6: begin
                    tens_digit = 88;
                    ones_digit = 6;
                end
                5: begin
                    tens_digit = 88;
                    ones_digit = 5;
                end
                4: begin
                    tens_digit = 88;
                    ones_digit = 4;
                end
                3: begin
                    tens_digit = 88;
                    ones_digit = 3;
                end
                2: begin
                    tens_digit = 88;
                    ones_digit = 2;
                end
                1: begin
                    tens_digit = 88;
                    ones_digit = 1;
                end
                default: begin
                    tens_digit = 9;
                    ones_digit = 9;
                end
            endcase
        end

    SevenSeg S1(.H(H0), .NUM(ones_digit));
    SevenSeg S2(.H(H1), .NUM(tens_digit));

endmodule

monthday.v
module monthday(
    input                       clk,
    input                       reset_n,
    input            [7:0]      cntr99,

	output           [7:0]      H0,
    output           [7:0]      H1,
    output           [7:0]      H2,

	//////////// SW //////////
	input 		     [9:0]		SW
);

    reg [7:0] month_d;
    reg[7:0] day_cntr;

    always @(cntr99)
        begin
            if(cntr99 <= 8'd31)
                begin
                month_d <= 8'd1;
                day_cntr <= cntr99;
                end
            else if(cntr99 <= 8'd59)
                begin
                    month_d <= 8'd2;
                    day_cntr <= cntr99 - 31;
                end
            else if(cntr99 <= 8'd90)
                begin
                    month_d <= 8'd3;
                    day_cntr <= cntr99 - 31 - 28;
                end
            else
                begin
                    month_d <= 8'd4;
                    day_cntr <= cntr99 - 31 - 28 - 31;
                end
        end

    SevenSeg S0(.H(H2), .NUM(month_d));

    daydisplay D0(.day_cntr(day_cntr), .H0(H0), .H1(H1));

endmodule

counters.v
module counters(
    input                       clk,
    input                       reset_n,

    output           [7:0]      H0,
    output           [7:0]      H1,
    output           [7:0]      H2,
	output		     [7:0]		H4,
	output		     [7:0]		H5,

    //////////// KEY //////////
	input 		     [1:0]		KEY,

	//////////// SW //////////
	input 		     [9:0]		SW
);

    reg [7:0] cntr1;
    reg [7:0] cntr2;
    reg [7:0] cntr99;

    always @(posedge clk, negedge reset_n)
        begin
            if(reset_n == 0)
                begin
                    cntr2 <= 8'd88;
                    cntr1 <= 8'd1;
                    cntr99 <= 8'd1;
                end
            else
                begin
                    if(cntr1 != 9)
                        begin
                            cntr2 <= cntr2;
                            cntr1 <= cntr1 + 1;
                            cntr99 <= cntr99 + 1;
                        end
                    else if(cntr1 == 9)
                        begin
                            if(cntr2 == 8'd88)
                                begin
                                    cntr2 <= 8'd1;
                                    cntr1 <= 8'd0;
                                    cntr99 <= cntr99 + 1;
                                end
                            else if(cntr2 == 8'd9)
                                begin
                                    cntr2 <= 8'd88;
                                    cntr1 <= 8'd1;
                                    cntr99 <= 8'd1;
                                end
                            else
                                begin
                                    cntr2 <= cntr2 + 1;
                                    cntr1 <= 8'd0;
                                    cntr99 <= cntr99 + 1;
                                end
                        end
                end
        end

    monthday M0(.clk(clk), .reset_n(reset_n), .cntr99(cntr99), .H0(H0), .H1(H1), .H2(H2), .SW(SW));

    SevenSeg W0(.H(H4), .NUM(cntr1));
    SevenSeg W1(.H(H5), .NUM(cntr2));

endmodule

Lab2.v

//=======================================================
//  This code is generated by Terasic System Builder
//=======================================================

module Lab2(

	//////////// CLOCK //////////
	input 		          		ADC_CLK_10,
	input 		          		MAX10_CLK1_50,
	input 		          		MAX10_CLK2_50,

	//////////// SEG7 //////////
	output		     [7:0]		HEX0,
	output		     [7:0]		HEX1,
	output		     [7:0]		HEX2,
	output		     [7:0]		HEX3,
	output		     [7:0]		HEX4,
	output		     [7:0]		HEX5,

	//////////// KEY //////////
	input 		     [1:0]		KEY,

	//////////// LED //////////
	output		     [9:0]		LEDR,

	//////////// SW //////////
	input 		     [9:0]		SW
);
	wire s_clk;
	reg latch_out = 1'b0;
	wire latch;

	SevenSeg T0(.H(HEX3), .NUM(8'd88));

	always @(negedge KEY[0])
		begin
			latch_out <= ~latch_out;	
		end

	assign latch = latch_out;
	assign LEDR[0] = ~latch_out;

	assign LEDR[1] = s_clk;

	clock_divider #(5_000_000) U0(.clk(ADC_CLK_10), .reset_n(latch), .slower_clk(s_clk));
	clock_divider #(1_000_000) U1(.clk(ADC_CLK_10), .reset_n(latch), .slower_clk(s_clk));

	reg div_val = 1'b1;
	wire val;

	always @(negedge KEY[1])
		begin
			div_val <= ~div_val;
		end

	assign val = div_val;

	// clock_choice L0(.);

	counters C0(.clk(s_clk), .reset_n(latch), .H0(HEX0), .H1(HEX1), .H2(HEX2), .H4(HEX4), .H5(HEX5), .KEY(KEY), .SW(SW));


endmodule

output.vcd
$date
	Mon Nov 04 22:42:43 2019
$end
$version
	Icarus Verilog
$end
$timescale
	100ps
$end
$scope module Lab2 $end
$var wire 1 ! ADC_CLK_10 $end
$var wire 2 " KEY [1:0] $end
$var wire 1 # MAX10_CLK1_50 $end
$var wire 1 $ MAX10_CLK2_50 $end
$var wire 10 % SW [9:0] $end
$var wire 1 & latch $end
$var wire 1 ' s_clk $end
$var wire 1 ( val $end
$var wire 10 ) LEDR [9:0] $end
$var wire 8 * HEX5 [7:0] $end
$var wire 8 + HEX4 [7:0] $end
$var wire 8 , HEX3 [7:0] $end
$var wire 8 - HEX2 [7:0] $end
$var wire 8 . HEX1 [7:0] $end
$var wire 8 / HEX0 [7:0] $end
$var reg 1 0 div_val $end
$var reg 1 1 latch_out $end
$scope module C0 $end
$var wire 2 2 KEY [1:0] $end
$var wire 10 3 SW [9:0] $end
$var wire 1 ' clk $end
$var wire 1 & reset_n $end
$var wire 8 4 H5 [7:0] $end
$var wire 8 5 H4 [7:0] $end
$var wire 8 6 H2 [7:0] $end
$var wire 8 7 H1 [7:0] $end
$var wire 8 8 H0 [7:0] $end
$var reg 8 9 cntr1 [7:0] $end
$var reg 8 : cntr2 [7:0] $end
$var reg 8 ; cntr99 [7:0] $end
$scope module M0 $end
$var wire 10 < SW [9:0] $end
$var wire 1 ' clk $end
$var wire 8 = cntr99 [7:0] $end
$var wire 1 & reset_n $end
$var wire 8 > H2 [7:0] $end
$var wire 8 ? H1 [7:0] $end
$var wire 8 @ H0 [7:0] $end
$var reg 8 A day_cntr [7:0] $end
$var reg 8 B month_d [7:0] $end
$scope module D0 $end
$var wire 8 C day_cntr [7:0] $end
$var wire 8 D H1 [7:0] $end
$var wire 8 E H0 [7:0] $end
$var reg 8 F ones_digit [7:0] $end
$var reg 8 G tens_digit [7:0] $end
$scope module S1 $end
$var wire 8 H H [7:0] $end
$var wire 8 I NUM [7:0] $end
$var reg 8 J value [7:0] $end
$upscope $end
$scope module S2 $end
$var wire 8 K H [7:0] $end
$var wire 8 L NUM [7:0] $end
$var reg 8 M value [7:0] $end
$upscope $end
$upscope $end
$scope module S0 $end
$var wire 8 N H [7:0] $end
$var wire 8 O NUM [7:0] $end
$var reg 8 P value [7:0] $end
$upscope $end
$upscope $end
$scope module W0 $end
$var wire 8 Q H [7:0] $end
$var wire 8 R NUM [7:0] $end
$var reg 8 S value [7:0] $end
$upscope $end
$scope module W1 $end
$var wire 8 T H [7:0] $end
$var wire 8 U NUM [7:0] $end
$var reg 8 V value [7:0] $end
$upscope $end
$upscope $end
$scope module T0 $end
$var wire 8 W H [7:0] $end
$var wire 8 X NUM [7:0] $end
$var reg 8 Y value [7:0] $end
$upscope $end
$scope module U0 $end
$var wire 1 ! clk $end
$var wire 1 & reset_n $end
$var wire 1 ' slower_clk $end
$var reg 24 Z div_cntr [23:0] $end
$var reg 1 [ slw_clk $end
$upscope $end
$scope module U1 $end
$var wire 1 ! clk $end
$var wire 1 & reset_n $end
$var wire 1 ' slower_clk $end
$var reg 24 \ div_cntr [23:0] $end
$var reg 1 ] slw_clk $end
$upscope $end
$upscope $end
$scope module tb_clkdiv $end
$var wire 1 ^ SCLK $end
$var reg 1 _ Rn $end
$var reg 1 ` clk $end
$scope module U0 $end
$var wire 1 ` clk $end
$var wire 1 _ reset_n $end
$var wire 1 ^ slower_clk $end
$var reg 24 a div_cntr [23:0] $end
$var reg 1 b slw_clk $end
$upscope $end
$upscope $end
$enddefinitions $end
#0
$dumpvars
0b
b0 a
0`
0_
0^
0]
b0 \
0[
b0 Z
b11111111 Y
b1011000 X
b11111111 W
b11111111 V
b1011000 U
b11111111 T
b11111001 S
b1 R
b11111001 Q
b11111001 P
b1 O
b11111001 N
b11111111 M
b1011000 L
b11111111 K
b11111001 J
b1 I
b11111001 H
b1011000 G
b1 F
b11111001 E
b11111111 D
b1 C
b1 B
b1 A
b11111001 @
b11111111 ?
b11111001 >
b1 =
bz <
b1 ;
b1011000 :
b1 9
b11111001 8
b11111111 7
b11111001 6
b11111001 5
b11111111 4
bz 3
bz 2
01
10
b11111001 /
b11111111 .
b11111001 -
b11111111 ,
b11111001 +
b11111111 *
bz01 )
1(
0'
0&
bz %
z$
z#
bz "
z!
$end
#50
1`
#100
0`
1_
#150
b1 a
1`
#200
0`
#250
b10 a
1`
#300
0`
#350
b11 a
1`
#400
0`
#450
b100 a
1`
#500
0`
#550
1^
1b
b0 a
1`
#600
0`
#650
b1 a
1`
#700
0`
#750
b10 a
1`
#800
0`
#850
b11 a
1`
#900
0`
#950
b100 a
1`
#1000
0`
#1050
0^
0b
b0 a
1`
#1100
0`
#1150
b1 a
1`
#1200
0`
#1250
b10 a
1`
#1300
0`
#1350
b11 a
1`
#1400
0`
#1450
b100 a
1`
#1500
0`
#1550
1^
1b
b0 a
1`
#1600
0`
#1650
b1 a
1`
#1700
0`
#1750
b10 a
1`
#1800
0`
#1850
b11 a
1`
#1900
0`
#1950
b100 a
1`
#2000
0`
#2050
0^
0b
b0 a
1`
#2100
0`
#2150
b1 a
1`
#2200
0`
#2250
b10 a
1`
#2300
0`
#2350
b11 a
1`
#2400
0`
#2450
b100 a
1`
#2500
0`
#2550
1^
1b
b0 a
1`
#2600
0`
#2650
b1 a
1`
#2700
0`
#2750
b10 a
1`
#2800
0`
#2850
b11 a
1`
#2900
0`
#2950
b100 a
1`
#3000
0`
#3050
0^
0b
b0 a
1`
#3100
0`
#3150
b1 a
1`
#3200
0`
#3250
b10 a
1`
#3300
0`
#3350
b11 a
1`
#3400
0`
#3450
b100 a
1`
#3500
0`
#3550
1^
1b
b0 a
1`
#3600
0`
#3650
b1 a
1`
#3700
0`
#3750
b10 a
1`
#3800
0`
#3850
b11 a
1`
#3900
0`
#3950
b100 a
1`
#4000
0`
#4050
0^
0b
b0 a
1`
#4100
0`
#4150
b1 a
1`
#4200
0`
#4250
b10 a
1`
#4300
0`
#4350
b11 a
1`
#4400
0`
#4450
b100 a
1`
#4500
0`
#4550
1^
1b
b0 a
1`
#4600
0`
#4650
b1 a
1`
#4700
0`
#4750
b10 a
1`
#4800
0`
#4850
b11 a
1`
#4900
0`
#4950
b100 a
1`
#5000
0`
#5050
0^
0b
b0 a
1`
#5100
0`
#5150
b1 a
1`
#5200
0`
#5250
b10 a
1`
#5300
0`
#5350
b11 a
1`
#5400
0`
#5450
b100 a
1`
#5500
0`
#5550
1^
1b
b0 a
1`
#5600
0`
#5650
b1 a
1`
#5700
0`
#5750
b10 a
1`
#5800
0`
#5850
b11 a
1`
#5900
0`
#5950
b100 a
1`
#6000
0`
#6050
0^
0b
b0 a
1`
#6100
0`
#6150
b1 a
1`
#6200
0`
#6250
b10 a
1`
#6300
0`
#6350
b11 a
1`
#6400
0`
#6450
b100 a
1`
#6500
0`
#6550
1^
1b
b0 a
1`
#6600
0`
#6650
b1 a
1`
#6700
0`
#6750
b10 a
1`
#6800
0`
#6850
b11 a
1`
#6900
0`
#6950
b100 a
1`
#7000
0`
#7050
0^
0b
b0 a
1`
#7100
0`
#7150
b1 a
1`
#7200
0`
#7250
b10 a
1`
#7300
0`
#7350
b11 a
1`
#7400
0`
#7450
b100 a
1`
#7500
0`
#7550
1^
1b
b0 a
1`
#7600
0`
#7650
b1 a
1`
#7700
0`
#7750
b10 a
1`
#7800
0`
#7850
b11 a
1`
#7900
0`
#7950
b100 a
1`
#8000
0`
#8050
0^
0b
b0 a
1`
#8100
0`
#8150
b1 a
1`
#8200
0`
#8250
b10 a
1`
#8300
0`
#8350
b11 a
1`
#8400
0`
#8450
b100 a
1`
#8500
0`
#8550
1^
1b
b0 a
1`
#8600
0`
#8650
b1 a
1`
#8700
0`
#8750
b10 a
1`
#8800
0`
#8850
b11 a
1`
#8900
0`
#8950
b100 a
1`
#9000
0`
#9050
0^
0b
b0 a
1`
#9100
0`
#9150
b1 a
1`
#9200
0`
#9250
b10 a
1`
#9300
0`
#9350
b11 a
1`
#9400
0`
#9450
b100 a
1`
#9500
0`
#9550
1^
1b
b0 a
1`
#9600
0`
#9650
b1 a
1`
#9700
0`
#9750
b10 a
1`
#9800
0`
#9850
b11 a
1`
#9900
0`
#9950
b100 a
1`
