SevenSeg.v
module SevenSeg(
 
    //////////// SEG7 //////////
    output           [7:0]      H,
 
    //////////// KEY //////////
    input            [7:0]     NUM
    
);
 
    reg [7:0] value;
 
//takes decimal number and converts to binary for HEX display based on logic 0 = on, logic 1 = off for each segment
//if NUM = 'd88 is blank(pos)
//if NUM = 'd99 is minus sign
    always @(NUM)
        begin
            case(NUM)
                8'd0: value = 8'b11000000;
                8'd1: value = 8'b11111001;
                8'd2: value = 8'b10100100;
                8'd3: value = 8'b10110000;
                8'd4: value = 8'b10011001;
                8'd5: value = 8'b10010010;
                8'd6: value = 8'b10000010;
                8'd7: value = 8'b11111000;
                8'd8: value = 8'b10000000;
                8'd9: value = 8'b10011000;
                8'd10: value = 8'b10001000; 
                8'd11: value = 8'b10000011;
                8'd12: value = 8'b11000110;
                8'd13: value = 8'b10100001;
                8'd14: value = 8'b10000110;
                8'd15: value = 8'b10001110;
 
                8'd88: value = 8'b11111111;
                8'd99: value = 8'b10111111;
            endcase
        end
 
 
    //the HEX display passed is given whatever value determined above
    assign H[7:0] = value;
 
 
endmodule

daydisplay.v
module daydisplay(
    // input                       clk,
    // input                       reset_n,
    input            [7:0]      day_cntr,

    output           [7:0]      H0,
    output           [7:0]      H1

	//////////// LED //////////
	// output		     [9:0]		LEDR,

	// //////////// SW //////////
	// input 		     [9:0]		SW
);

    reg [7:0] ones_digit;
    reg [7:0] tens_digit;

    always @(day_cntr)begin
            case (day_cntr)
                31: begin
                    tens_digit = 3;
                    ones_digit = 1;
                end
                30: begin
                    tens_digit = 3;
                    ones_digit = 0;
                end
                29: begin
                    tens_digit = 2;
                    ones_digit = 9;
                end
                28: begin
                    tens_digit = 2;
                    ones_digit = 8;
                end
                27: begin
                    tens_digit = 2;
                    ones_digit = 7;
                end
                26: begin
                    tens_digit = 2;
                    ones_digit = 6;
                end
                25: begin
                    tens_digit = 2;
                    ones_digit = 5;
                end
                24: begin
                    tens_digit = 2;
                    ones_digit = 4;
                end
                23: begin
                    tens_digit = 2;
                    ones_digit = 3;
                end
                22: begin
                    tens_digit = 2;
                    ones_digit = 2;
                end
                21: begin
                    tens_digit = 2;
                    ones_digit = 1;
                end
                20: begin
                    tens_digit = 2;
                    ones_digit = 0;
                end
                19: begin
                    tens_digit = 1;
                    ones_digit = 9;
                end
                18: begin
                    tens_digit = 1;
                    ones_digit = 8;
                end
                17: begin
                    tens_digit = 1;
                    ones_digit = 7;
                end
                16: begin
                    tens_digit = 1;
                    ones_digit = 6;
                end
                15: begin
                    tens_digit = 1;
                    ones_digit = 5;
                end
                14: begin
                    tens_digit = 1;
                    ones_digit = 4;
                end
                13: begin
                    tens_digit = 1;
                    ones_digit = 3;
                end
                12: begin
                    tens_digit = 1;
                    ones_digit = 2;
                end
                11: begin
                    tens_digit = 1;
                    ones_digit = 1;
                end
                10: begin
                    tens_digit = 1;
                    ones_digit = 0;
                end
                9: begin
                    tens_digit = 88;
                    ones_digit = 9;
                end
                8: begin
                    tens_digit = 88;
                    ones_digit = 8;
                end
                7: begin
                    tens_digit = 88;
                    ones_digit = 7;
                end
                6: begin
                    tens_digit = 88;
                    ones_digit = 6;
                end
                5: begin
                    tens_digit = 88;
                    ones_digit = 5;
                end
                4: begin
                    tens_digit = 88;
                    ones_digit = 4;
                end
                3: begin
                    tens_digit = 88;
                    ones_digit = 3;
                end
                2: begin
                    tens_digit = 88;
                    ones_digit = 2;
                end
                1: begin
                    tens_digit = 88;
                    ones_digit = 1;
                end
                default: begin
                    tens_digit = 9;
                    ones_digit = 9;
                end
            endcase
        end

    SevenSeg S1(.H(H0), .NUM(ones_digit));
    SevenSeg S2(.H(H1), .NUM(tens_digit));

endmodule

monthday.v
module monthday(
    input                       clk,
    input                       reset_n,
    input            [7:0]      cntr99,
    input            [7:0]      feb_day,

	output           [7:0]      H0,
    output           [7:0]      H1,
    output           [7:0]      H2,

	//////////// SW //////////
	input 		     [9:0]		SW
);

    reg [7:0] month_d;
    reg [7:0] day_cntr;

    always @(cntr99)
        begin
            if(cntr99 <= 8'd31)
                begin
                month_d <= 8'd1;
                day_cntr <= cntr99;
                end
            else if(cntr99 <= (8'd31 + feb_day))
                begin
                    month_d <= 8'd2;
                    day_cntr <= cntr99 - 31;
                end
            else if(cntr99 <= (8'd31 + feb_day + 8'd31))
                begin
                    month_d <= 8'd3;
                    day_cntr <= cntr99 - (8'd31 + feb_day);
                end
            else
                begin
                    month_d <= 8'd4;
                    day_cntr <= cntr99 - (8'd31 + feb_day + 8'd31);
                end
        end

    SevenSeg S0(.H(H2), .NUM(month_d));

    daydisplay D0(.day_cntr(day_cntr), .H0(H0), .H1(H1));

endmodule

counters.v
module counters(
    input                       clk,
    input                       reset_n,
    input            [7:0]     feb_day,

    output           [7:0]      H0,
    output           [7:0]      H1,
    output           [7:0]      H2,
	output		     [7:0]		H4,
	output		     [7:0]		H5,

    //////////// KEY //////////
	input 		     [1:0]		KEY,

	//////////// SW //////////
	input 		     [9:0]		SW
);

    reg [7:0] cntr1;
    reg [7:0] cntr2;
    reg [7:0] cntr99;

    always @(posedge clk, negedge reset_n)
        begin
            if(reset_n == 0)
                begin
                    cntr2 <= 8'd88;
                    cntr1 <= 8'd1;
                    cntr99 <= 8'd1;
                end
            else
                begin
                    if(cntr1 != 9)
                        begin
                            cntr2 <= cntr2;
                            cntr1 <= cntr1 + 1;
                            cntr99 <= cntr99 + 1;
                        end
                    else if(cntr1 == 9)
                        begin
                            if(cntr2 == 8'd88)
                                begin
                                    cntr2 <= 8'd1;
                                    cntr1 <= 8'd0;
                                    cntr99 <= cntr99 + 1;
                                end
                            else if(cntr2 == 8'd9)
                                begin
                                    cntr2 <= 8'd88;
                                    cntr1 <= 8'd1;
                                    cntr99 <= 8'd1;
                                end
                            else
                                begin
                                    cntr2 <= cntr2 + 1;
                                    cntr1 <= 8'd0;
                                    cntr99 <= cntr99 + 1;
                                end
                        end
                end
        end

    monthday M0(.clk(clk), .reset_n(reset_n), .cntr99(cntr99), .feb_day(feb_day), .H0(H0), .H1(H1), .H2(H2), .SW(SW));

    SevenSeg W0(.H(H4), .NUM(cntr1));
    SevenSeg W1(.H(H5), .NUM(cntr2));

endmodule

tb_BCD.v
`timescale 1 ns / 100 ps

module tb_BCD();

    reg clk;
    reg Rn;
    wire [7:0] HEX0;
    wire [7:0] HEX1;
    wire [7:0] HEX2;
    wire [7:0] HEX4;
    wire [7:0] HEX5;
    wire [1:0] K;
    wire [9:0] sw;

    counters U0 (
        .clk(clk),
        .reset_n(Rn),
        .H0(HEX0),
        .H1(HEX1),
        .H2(HEX2),
        .H4(HEX4),
        .H5(HEX5),
        .KEY(K),
        .SW(sw)
    );

    initial
        begin
            clk = 1'b0;
            Rn = 1'b0;
        #10 Rn = 1'b1;
        end

    always
        #5 clk = ~clk;

    initial
        begin
            $dumpfile("output.vcd");
            $dumpvars;
            $display("Starting simulation");
        end   

    initial
        begin
        $monitor("%d,\t%b,\t%b,\t%d", $time, clk, Rn, HEX4, HEX5);        
        end

        initial
            begin
            $display("Simulation ended.");
            #1300 $finish;
            end
        
endmodule

clock_choice.v
module clock_choice(

    input                       select,

    input                        latch,
    output                       s_clk,

	input                        s1,
    input                 [0:0]  s2
);

    reg SCLK;
    
    assign s_clk = SCLK;

    always @(select)
        begin
            case(select)
                0: SCLK = s1;
                1: SCLK = s2;
            endcase 
        end

    assign s_clk = SCLK;

endmodule

clock_divider.v
module clock_divider(

	//////////// CLOCK //////////
	input 		          		clk,
    input                       reset_n,
    output                      slower_clk      //calculate correct size!                
);

    parameter clk_div = 0;

    reg [23:0] div_cntr; //calculate correct size!
    reg slw_clk;

    always @(posedge clk, negedge reset_n)
        begin
            if(reset_n == 0)
                begin
                    div_cntr <= 0;
                    slw_clk <= 0;
                end
            else if(div_cntr == clk_div - 1)
                begin
                    div_cntr <= 0;
                    slw_clk <= ~slw_clk;
                end
            else
                begin
                    div_cntr <= div_cntr + 1;
                end
        end

    assign slower_clk = slw_clk;

endmodule

Lab2.v

//=======================================================
//  This code is generated by Terasic System Builder
//=======================================================

module Lab2(

	//////////// CLOCK //////////
	input 		          		ADC_CLK_10,

	//////////// SEG7 //////////
	output		     [7:0]		HEX0,
	output		     [7:0]		HEX1,
	output		     [7:0]		HEX2,
	output		     [7:0]		HEX3,
	output		     [7:0]		HEX4,
	output		     [7:0]		HEX5,

	//////////// KEY //////////
	input 		     [1:0]		KEY,

	//////////// LED //////////
	output		     [9:0]		LEDR,

	//////////// SW //////////
	input 		     [9:0]		SW
);
	wire s_clk;
	wire s_clk1;
	wire s_clk2;
	reg latch_out = 1'b0;
	wire latch;

	SevenSeg T0(.H(HEX3), .NUM(8'd88));

	always @(negedge KEY[0])
		begin
			latch_out <= ~latch_out;	
		end

	assign latch = latch_out;
	assign LEDR[0] = latch_out;

	assign LEDR[1] = s_clk;

	reg [7:0] feb_day;
	
		always @(SW[9])
			begin
				if(SW[9] == 1)
					feb_day <= 8'd29;
				else
					feb_day <= 8'd28;
			end

	reg div_val = 1'b1;
	wire val;

	always @(negedge KEY[1])
		begin
			div_val <= ~div_val;
		end

	assign val = div_val;
	
	clock_divider #(1_000_000) U0(.clk(ADC_CLK_10), .reset_n(latch), .slower_clk(s_clk1));
	clock_divider #(5_000_000) U1(.clk(ADC_CLK_10), .reset_n(latch), .slower_clk(s_clk2));

	clock_choice L0(.select(val), .latch(latch), .s_clk(s_clk), .s1(s_clk1), .s2(s_clk2));

	counters C0(.clk(s_clk), .reset_n(latch), .feb_day(feb_day), .H0(HEX0), .H1(HEX1), .H2(HEX2), .H4(HEX4), .H5(HEX5), .KEY(KEY), .SW(SW));


endmodule

output.vcd
$date
	Wed Nov 06 21:46:08 2019
$end
$version
	Icarus Verilog
$end
$timescale
	100ps
$end
$scope module Lab2 $end
$var wire 1 ! ADC_CLK_10 $end
$var wire 2 " KEY [1:0] $end
$var wire 10 # SW [9:0] $end
$var wire 1 $ latch $end
$var wire 1 % s_clk $end
$var wire 1 & val $end
$var wire 1 ' s_clk2 $end
$var wire 1 ( s_clk1 $end
$var wire 10 ) LEDR [9:0] $end
$var wire 8 * HEX5 [7:0] $end
$var wire 8 + HEX4 [7:0] $end
$var wire 8 , HEX3 [7:0] $end
$var wire 8 - HEX2 [7:0] $end
$var wire 8 . HEX1 [7:0] $end
$var wire 8 / HEX0 [7:0] $end
$var reg 1 0 div_val $end
$var reg 8 1 feb_day [7:0] $end
$var reg 1 2 latch_out $end
$scope module C0 $end
$var wire 2 3 KEY [1:0] $end
$var wire 10 4 SW [9:0] $end
$var wire 1 % clk $end
$var wire 8 5 feb_day [7:0] $end
$var wire 1 $ reset_n $end
$var wire 8 6 H5 [7:0] $end
$var wire 8 7 H4 [7:0] $end
$var wire 8 8 H2 [7:0] $end
$var wire 8 9 H1 [7:0] $end
$var wire 8 : H0 [7:0] $end
$var reg 8 ; cntr1 [7:0] $end
$var reg 8 < cntr2 [7:0] $end
$var reg 8 = cntr99 [7:0] $end
$scope module M0 $end
$var wire 10 > SW [9:0] $end
$var wire 1 % clk $end
$var wire 8 ? cntr99 [7:0] $end
$var wire 8 @ feb_day [7:0] $end
$var wire 1 $ reset_n $end
$var wire 8 A H2 [7:0] $end
$var wire 8 B H1 [7:0] $end
$var wire 8 C H0 [7:0] $end
$var reg 8 D day_cntr [7:0] $end
$var reg 8 E month_d [7:0] $end
$scope module D0 $end
$var wire 8 F day_cntr [7:0] $end
$var wire 8 G H1 [7:0] $end
$var wire 8 H H0 [7:0] $end
$var reg 8 I ones_digit [7:0] $end
$var reg 8 J tens_digit [7:0] $end
$scope module S1 $end
$var wire 8 K H [7:0] $end
$var wire 8 L NUM [7:0] $end
$var reg 8 M value [7:0] $end
$upscope $end
$scope module S2 $end
$var wire 8 N H [7:0] $end
$var wire 8 O NUM [7:0] $end
$var reg 8 P value [7:0] $end
$upscope $end
$upscope $end
$scope module S0 $end
$var wire 8 Q H [7:0] $end
$var wire 8 R NUM [7:0] $end
$var reg 8 S value [7:0] $end
$upscope $end
$upscope $end
$scope module W0 $end
$var wire 8 T H [7:0] $end
$var wire 8 U NUM [7:0] $end
$var reg 8 V value [7:0] $end
$upscope $end
$scope module W1 $end
$var wire 8 W H [7:0] $end
$var wire 8 X NUM [7:0] $end
$var reg 8 Y value [7:0] $end
$upscope $end
$upscope $end
$scope module L0 $end
$var wire 1 $ latch $end
$var wire 1 % s_clk $end
$var wire 1 & select $end
$var wire 1 ' s2 $end
$var wire 1 ( s1 $end
$var reg 1 Z SCLK $end
$upscope $end
$scope module T0 $end
$var wire 8 [ H [7:0] $end
$var wire 8 \ NUM [7:0] $end
$var reg 8 ] value [7:0] $end
$upscope $end
$scope module U0 $end
$var wire 1 ! clk $end
$var wire 1 $ reset_n $end
$var wire 1 ( slower_clk $end
$var reg 24 ^ div_cntr [23:0] $end
$var reg 1 _ slw_clk $end
$upscope $end
$scope module U1 $end
$var wire 1 ! clk $end
$var wire 1 $ reset_n $end
$var wire 1 ' slower_clk $end
$var reg 24 ` div_cntr [23:0] $end
$var reg 1 a slw_clk $end
$upscope $end
$upscope $end
$scope module tb_BCD $end
$var wire 2 b K [1:0] $end
$var wire 10 c sw [9:0] $end
$var wire 8 d HEX5 [7:0] $end
$var wire 8 e HEX4 [7:0] $end
$var wire 8 f HEX2 [7:0] $end
$var wire 8 g HEX1 [7:0] $end
$var wire 8 h HEX0 [7:0] $end
$var reg 1 i Rn $end
$var reg 1 j clk $end
$scope module U0 $end
$var wire 2 k KEY [1:0] $end
$var wire 10 l SW [9:0] $end
$var wire 1 j clk $end
$var wire 8 m feb_day [7:0] $end
$var wire 1 i reset_n $end
$var wire 8 n H5 [7:0] $end
$var wire 8 o H4 [7:0] $end
$var wire 8 p H2 [7:0] $end
$var wire 8 q H1 [7:0] $end
$var wire 8 r H0 [7:0] $end
$var reg 8 s cntr1 [7:0] $end
$var reg 8 t cntr2 [7:0] $end
$var reg 8 u cntr99 [7:0] $end
$scope module M0 $end
$var wire 10 v SW [9:0] $end
$var wire 1 j clk $end
$var wire 8 w cntr99 [7:0] $end
$var wire 8 x feb_day [7:0] $end
$var wire 1 i reset_n $end
$var wire 8 y H2 [7:0] $end
$var wire 8 z H1 [7:0] $end
$var wire 8 { H0 [7:0] $end
$var reg 8 | day_cntr [7:0] $end
$var reg 8 } month_d [7:0] $end
$scope module D0 $end
$var wire 8 ~ day_cntr [7:0] $end
$var wire 8 !" H1 [7:0] $end
$var wire 8 "" H0 [7:0] $end
$var reg 8 #" ones_digit [7:0] $end
$var reg 8 $" tens_digit [7:0] $end
$scope module S1 $end
$var wire 8 %" H [7:0] $end
$var wire 8 &" NUM [7:0] $end
$var reg 8 '" value [7:0] $end
$upscope $end
$scope module S2 $end
$var wire 8 (" H [7:0] $end
$var wire 8 )" NUM [7:0] $end
$var reg 8 *" value [7:0] $end
$upscope $end
$upscope $end
$scope module S0 $end
$var wire 8 +" H [7:0] $end
$var wire 8 ," NUM [7:0] $end
$var reg 8 -" value [7:0] $end
$upscope $end
$upscope $end
$scope module W0 $end
$var wire 8 ." H [7:0] $end
$var wire 8 /" NUM [7:0] $end
$var reg 8 0" value [7:0] $end
$upscope $end
$scope module W1 $end
$var wire 8 1" H [7:0] $end
$var wire 8 2" NUM [7:0] $end
$var reg 8 3" value [7:0] $end
$upscope $end
$upscope $end
$upscope $end
$enddefinitions $end
#0
$dumpvars
b11111111 3"
b1011000 2"
b11111111 1"
b11111001 0"
b1 /"
b11111001 ."
b11111001 -"
b1 ,"
b11111001 +"
b11111111 *"
b1011000 )"
b11111111 ("
b11111001 '"
b1 &"
b11111001 %"
b1011000 $"
b1 #"
b11111001 ""
b11111111 !"
b1 ~
b1 }
b1 |
b11111001 {
b11111111 z
b11111001 y
bz x
b1 w
bz v
b1 u
b1011000 t
b1 s
b11111001 r
b11111111 q
b11111001 p
b11111001 o
b11111111 n
bz m
bz l
bz k
0j
0i
b11111001 h
b11111111 g
b11111001 f
b11111001 e
b11111111 d
bz c
bz b
0a
b0 `
0_
b0 ^
b11111111 ]
b1011000 \
b11111111 [
xZ
b11111111 Y
b1011000 X
b11111111 W
b11111001 V
b1 U
b11111001 T
b11111001 S
b1 R
b11111001 Q
b11111111 P
b1011000 O
b11111111 N
b11111001 M
b1 L
b11111001 K
b1011000 J
b1 I
b11111001 H
b11111111 G
b1 F
b1 E
b1 D
b11111001 C
b11111111 B
b11111001 A
b11100 @
b1 ?
bz >
b1 =
b1011000 <
b1 ;
b11111001 :
b11111111 9
b11111001 8
b11111001 7
b11111111 6
b11100 5
bz 4
bz 3
02
b11100 1
10
b11111001 /
b11111111 .
b11111001 -
b11111111 ,
b11111001 +
b11111111 *
bzx0 )
0(
0'
1&
x%
0$
bz #
bz "
z!
$end
#50
1j
#100
0j
1i
#150
b10100100 h
b10100100 r
b10100100 {
b10100100 ""
b10100100 %"
b10100100 '"
b10 #"
b10 &"
b10 |
b10 ~
b10100100 e
b10100100 o
b10100100 ."
b10100100 0"
b10 u
b10 w
b10 s
b10 /"
1j
#200
0j
#250
b10110000 h
b10110000 r
b10110000 {
b10110000 ""
b10110000 %"
b10110000 '"
b11 #"
b11 &"
b11 |
b11 ~
b10110000 e
b10110000 o
b10110000 ."
b10110000 0"
b11 u
b11 w
b11 s
b11 /"
1j
#300
0j
#350
b10011001 h
b10011001 r
b10011001 {
b10011001 ""
b10011001 %"
b10011001 '"
b100 #"
b100 &"
b100 |
b100 ~
b10011001 e
b10011001 o
b10011001 ."
b10011001 0"
b100 u
b100 w
b100 s
b100 /"
1j
#400
0j
#450
b10010010 h
b10010010 r
b10010010 {
b10010010 ""
b10010010 %"
b10010010 '"
b101 #"
b101 &"
b101 |
b101 ~
b10010010 e
b10010010 o
b10010010 ."
b10010010 0"
b101 u
b101 w
b101 s
b101 /"
1j
#500
0j
#550
b10000010 h
b10000010 r
b10000010 {
b10000010 ""
b10000010 %"
b10000010 '"
b110 #"
b110 &"
b110 |
b110 ~
b10000010 e
b10000010 o
b10000010 ."
b10000010 0"
b110 u
b110 w
b110 s
b110 /"
1j
#600
0j
#650
b11111000 h
b11111000 r
b11111000 {
b11111000 ""
b11111000 %"
b11111000 '"
b111 #"
b111 &"
b111 |
b111 ~
b11111000 e
b11111000 o
b11111000 ."
b11111000 0"
b111 u
b111 w
b111 s
b111 /"
1j
#700
0j
#750
b10000000 h
b10000000 r
b10000000 {
b10000000 ""
b10000000 %"
b10000000 '"
b1000 #"
b1000 &"
b1000 |
b1000 ~
b10000000 e
b10000000 o
b10000000 ."
b10000000 0"
b1000 u
b1000 w
b1000 s
b1000 /"
1j
#800
0j
#850
b10011000 h
b10011000 r
b10011000 {
b10011000 ""
b10011000 %"
b10011000 '"
b1001 #"
b1001 &"
b1001 |
b1001 ~
b10011000 e
b10011000 o
b10011000 ."
b10011000 0"
b1001 u
b1001 w
b1001 s
b1001 /"
1j
#900
0j
#950
b11000000 h
b11000000 r
b11000000 {
b11000000 ""
b11000000 %"
b11000000 '"
b11111001 g
b11111001 q
b11111001 z
b11111001 !"
b11111001 ("
b11111001 *"
b0 #"
b0 &"
b1 $"
b1 )"
b1010 |
b1010 ~
b11000000 e
b11000000 o
b11000000 ."
b11000000 0"
b11111001 d
b11111001 n
b11111001 1"
b11111001 3"
b1010 u
b1010 w
b0 s
b0 /"
b1 t
b1 2"
1j
#1000
0j
#1050
b11111001 h
b11111001 r
b11111001 {
b11111001 ""
b11111001 %"
b11111001 '"
b1 #"
b1 &"
b1011 |
b1011 ~
b11111001 e
b11111001 o
b11111001 ."
b11111001 0"
b1011 u
b1011 w
b1 s
b1 /"
1j
#1100
0j
#1150
b10100100 h
b10100100 r
b10100100 {
b10100100 ""
b10100100 %"
b10100100 '"
b10 #"
b10 &"
b1100 |
b1100 ~
b10100100 e
b10100100 o
b10100100 ."
b10100100 0"
b1100 u
b1100 w
b10 s
b10 /"
1j
#1200
0j
#1250
b10110000 h
b10110000 r
b10110000 {
b10110000 ""
b10110000 %"
b10110000 '"
b11 #"
b11 &"
b1101 |
b1101 ~
b10110000 e
b10110000 o
b10110000 ."
b10110000 0"
b1101 u
b1101 w
b11 s
b11 /"
1j
#1300
0j
#1350
b10011001 h
b10011001 r
b10011001 {
b10011001 ""
b10011001 %"
b10011001 '"
b100 #"
b100 &"
b1110 |
b1110 ~
b10011001 e
b10011001 o
b10011001 ."
b10011001 0"
b1110 u
b1110 w
b100 s
b100 /"
1j
#1400
0j
#1450
b10010010 h
b10010010 r
b10010010 {
b10010010 ""
b10010010 %"
b10010010 '"
b101 #"
b101 &"
b1111 |
b1111 ~
b10010010 e
b10010010 o
b10010010 ."
b10010010 0"
b1111 u
b1111 w
b101 s
b101 /"
1j
#1500
0j
#1550
b10000010 h
b10000010 r
b10000010 {
b10000010 ""
b10000010 %"
b10000010 '"
b110 #"
b110 &"
b10000 |
b10000 ~
b10000010 e
b10000010 o
b10000010 ."
b10000010 0"
b10000 u
b10000 w
b110 s
b110 /"
1j
#1600
0j
#1650
b11111000 h
b11111000 r
b11111000 {
b11111000 ""
b11111000 %"
b11111000 '"
b111 #"
b111 &"
b10001 |
b10001 ~
b11111000 e
b11111000 o
b11111000 ."
b11111000 0"
b10001 u
b10001 w
b111 s
b111 /"
1j
#1700
0j
#1750
b10000000 h
b10000000 r
b10000000 {
b10000000 ""
b10000000 %"
b10000000 '"
b1000 #"
b1000 &"
b10010 |
b10010 ~
b10000000 e
b10000000 o
b10000000 ."
b10000000 0"
b10010 u
b10010 w
b1000 s
b1000 /"
1j
#1800
0j
#1850
b10011000 h
b10011000 r
b10011000 {
b10011000 ""
b10011000 %"
b10011000 '"
b1001 #"
b1001 &"
b10011 |
b10011 ~
b10011000 e
b10011000 o
b10011000 ."
b10011000 0"
b10011 u
b10011 w
b1001 s
b1001 /"
1j
#1900
0j
#1950
b11000000 h
b11000000 r
b11000000 {
b11000000 ""
b11000000 %"
b11000000 '"
b10100100 g
b10100100 q
b10100100 z
b10100100 !"
b10100100 ("
b10100100 *"
b0 #"
b0 &"
b10 $"
b10 )"
b10100 |
b10100 ~
b11000000 e
b11000000 o
b11000000 ."
b11000000 0"
b10100100 d
b10100100 n
b10100100 1"
b10100100 3"
b10100 u
b10100 w
b0 s
b0 /"
b10 t
b10 2"
1j
#2000
0j
#2050
b11111001 h
b11111001 r
b11111001 {
b11111001 ""
b11111001 %"
b11111001 '"
b1 #"
b1 &"
b10101 |
b10101 ~
b11111001 e
b11111001 o
b11111001 ."
b11111001 0"
b10101 u
b10101 w
b1 s
b1 /"
1j
#2100
0j
#2150
b10100100 h
b10100100 r
b10100100 {
b10100100 ""
b10100100 %"
b10100100 '"
b10 #"
b10 &"
b10110 |
b10110 ~
b10100100 e
b10100100 o
b10100100 ."
b10100100 0"
b10110 u
b10110 w
b10 s
b10 /"
1j
#2200
0j
#2250
b10110000 h
b10110000 r
b10110000 {
b10110000 ""
b10110000 %"
b10110000 '"
b11 #"
b11 &"
b10111 |
b10111 ~
b10110000 e
b10110000 o
b10110000 ."
b10110000 0"
b10111 u
b10111 w
b11 s
b11 /"
1j
#2300
0j
#2350
b10011001 h
b10011001 r
b10011001 {
b10011001 ""
b10011001 %"
b10011001 '"
b100 #"
b100 &"
b11000 |
b11000 ~
b10011001 e
b10011001 o
b10011001 ."
b10011001 0"
b11000 u
b11000 w
b100 s
b100 /"
1j
#2400
0j
#2450
b10010010 h
b10010010 r
b10010010 {
b10010010 ""
b10010010 %"
b10010010 '"
b101 #"
b101 &"
b11001 |
b11001 ~
b10010010 e
b10010010 o
b10010010 ."
b10010010 0"
b11001 u
b11001 w
b101 s
b101 /"
1j
#2500
0j
#2550
b10000010 h
b10000010 r
b10000010 {
b10000010 ""
b10000010 %"
b10000010 '"
b110 #"
b110 &"
b11010 |
b11010 ~
b10000010 e
b10000010 o
b10000010 ."
b10000010 0"
b11010 u
b11010 w
b110 s
b110 /"
1j
#2600
0j
#2650
b11111000 h
b11111000 r
b11111000 {
b11111000 ""
b11111000 %"
b11111000 '"
b111 #"
b111 &"
b11011 |
b11011 ~
b11111000 e
b11111000 o
b11111000 ."
b11111000 0"
b11011 u
b11011 w
b111 s
b111 /"
1j
#2700
0j
#2750
b10000000 h
b10000000 r
b10000000 {
b10000000 ""
b10000000 %"
b10000000 '"
b1000 #"
b1000 &"
b11100 |
b11100 ~
b10000000 e
b10000000 o
b10000000 ."
b10000000 0"
b11100 u
b11100 w
b1000 s
b1000 /"
1j
#2800
0j
#2850
b10011000 h
b10011000 r
b10011000 {
b10011000 ""
b10011000 %"
b10011000 '"
b1001 #"
b1001 &"
b11101 |
b11101 ~
b10011000 e
b10011000 o
b10011000 ."
b10011000 0"
b11101 u
b11101 w
b1001 s
b1001 /"
1j
#2900
0j
#2950
b11000000 h
b11000000 r
b11000000 {
b11000000 ""
b11000000 %"
b11000000 '"
b10110000 g
b10110000 q
b10110000 z
b10110000 !"
b10110000 ("
b10110000 *"
b0 #"
b0 &"
b11 $"
b11 )"
b11110 |
b11110 ~
b11000000 e
b11000000 o
b11000000 ."
b11000000 0"
b10110000 d
b10110000 n
b10110000 1"
b10110000 3"
b11110 u
b11110 w
b0 s
b0 /"
b11 t
b11 2"
1j
#3000
0j
#3050
b11111001 h
b11111001 r
b11111001 {
b11111001 ""
b11111001 %"
b11111001 '"
b1 #"
b1 &"
b11111 |
b11111 ~
b11111001 e
b11111001 o
b11111001 ."
b11111001 0"
b11111 u
b11111 w
b1 s
b1 /"
1j
#3100
0j
#3150
b10011000 h
b10011000 r
b10011000 {
b10011000 ""
b10011000 %"
b10011000 '"
b10011000 g
b10011000 q
b10011000 z
b10011000 !"
b10011000 ("
b10011000 *"
b1001 #"
b1001 &"
b1001 $"
b1001 )"
b10011001 f
b10011001 p
b10011001 y
b10011001 +"
b10011001 -"
bx |
bx ~
b100 }
b100 ,"
b10100100 e
b10100100 o
b10100100 ."
b10100100 0"
b100000 u
b100000 w
b10 s
b10 /"
1j
#3200
0j
#3250
b10110000 e
b10110000 o
b10110000 ."
b10110000 0"
b100001 u
b100001 w
b11 s
b11 /"
1j
#3300
0j
#3350
b10011001 e
b10011001 o
b10011001 ."
b10011001 0"
b100010 u
b100010 w
b100 s
b100 /"
1j
#3400
0j
#3450
b10010010 e
b10010010 o
b10010010 ."
b10010010 0"
b100011 u
b100011 w
b101 s
b101 /"
1j
#3500
0j
#3550
b10000010 e
b10000010 o
b10000010 ."
b10000010 0"
b100100 u
b100100 w
b110 s
b110 /"
1j
#3600
0j
#3650
b11111000 e
b11111000 o
b11111000 ."
b11111000 0"
b100101 u
b100101 w
b111 s
b111 /"
1j
#3700
0j
#3750
b10000000 e
b10000000 o
b10000000 ."
b10000000 0"
b100110 u
b100110 w
b1000 s
b1000 /"
1j
#3800
0j
#3850
b10011000 e
b10011000 o
b10011000 ."
b10011000 0"
b100111 u
b100111 w
b1001 s
b1001 /"
1j
#3900
0j
#3950
b11000000 e
b11000000 o
b11000000 ."
b11000000 0"
b10011001 d
b10011001 n
b10011001 1"
b10011001 3"
b101000 u
b101000 w
b0 s
b0 /"
b100 t
b100 2"
1j
#4000
0j
#4050
b11111001 e
b11111001 o
b11111001 ."
b11111001 0"
b101001 u
b101001 w
b1 s
b1 /"
1j
#4100
0j
#4150
b10100100 e
b10100100 o
b10100100 ."
b10100100 0"
b101010 u
b101010 w
b10 s
b10 /"
1j
#4200
0j
#4250
b10110000 e
b10110000 o
b10110000 ."
b10110000 0"
b101011 u
b101011 w
b11 s
b11 /"
1j
#4300
0j
#4350
b10011001 e
b10011001 o
b10011001 ."
b10011001 0"
b101100 u
b101100 w
b100 s
b100 /"
1j
#4400
0j
#4450
b10010010 e
b10010010 o
b10010010 ."
b10010010 0"
b101101 u
b101101 w
b101 s
b101 /"
1j
#4500
0j
#4550
b10000010 e
b10000010 o
b10000010 ."
b10000010 0"
b101110 u
b101110 w
b110 s
b110 /"
1j
#4600
0j
#4650
b11111000 e
b11111000 o
b11111000 ."
b11111000 0"
b101111 u
b101111 w
b111 s
b111 /"
1j
#4700
0j
#4750
b10000000 e
b10000000 o
b10000000 ."
b10000000 0"
b110000 u
b110000 w
b1000 s
b1000 /"
1j
#4800
0j
#4850
b10011000 e
b10011000 o
b10011000 ."
b10011000 0"
b110001 u
b110001 w
b1001 s
b1001 /"
1j
#4900
0j
#4950
b11000000 e
b11000000 o
b11000000 ."
b11000000 0"
b10010010 d
b10010010 n
b10010010 1"
b10010010 3"
b110010 u
b110010 w
b0 s
b0 /"
b101 t
b101 2"
1j
#5000
0j
#5050
b11111001 e
b11111001 o
b11111001 ."
b11111001 0"
b110011 u
b110011 w
b1 s
b1 /"
1j
#5100
0j
#5150
b10100100 e
b10100100 o
b10100100 ."
b10100100 0"
b110100 u
b110100 w
b10 s
b10 /"
1j
#5200
0j
#5250
b10110000 e
b10110000 o
b10110000 ."
b10110000 0"
b110101 u
b110101 w
b11 s
b11 /"
1j
#5300
0j
#5350
b10011001 e
b10011001 o
b10011001 ."
b10011001 0"
b110110 u
b110110 w
b100 s
b100 /"
1j
#5400
0j
#5450
b10010010 e
b10010010 o
b10010010 ."
b10010010 0"
b110111 u
b110111 w
b101 s
b101 /"
1j
#5500
0j
#5550
b10000010 e
b10000010 o
b10000010 ."
b10000010 0"
b111000 u
b111000 w
b110 s
b110 /"
1j
#5600
0j
#5650
b11111000 e
b11111000 o
b11111000 ."
b11111000 0"
b111001 u
b111001 w
b111 s
b111 /"
1j
#5700
0j
#5750
b10000000 e
b10000000 o
b10000000 ."
b10000000 0"
b111010 u
b111010 w
b1000 s
b1000 /"
1j
#5800
0j
